potterdb/__init__.py
potterdb/potterdb.py
potterdb-0.4.0.dist-info/LICENSE
potterdb-0.4.0.dist-info/METADATA
potterdb-0.4.0.dist-info/WHEEL
potterdb-0.4.0.dist-info/RECORD
